README.md
setup.py
anubis_openapi_kernel.egg-info/PKG-INFO
anubis_openapi_kernel.egg-info/SOURCES.txt
anubis_openapi_kernel.egg-info/dependency_links.txt
anubis_openapi_kernel.egg-info/requires.txt
anubis_openapi_kernel.egg-info/top_level.txt
kernel/__init__.py
kernel/client.py
kernel/config.py
kernel/context.py